ir2json/__init__.py
ir2json/__main__.py
ir2json/convert_to_json_ir.py
ir2json-1.0.0.dist-info/LICENSE
ir2json-1.0.0.dist-info/METADATA
ir2json-1.0.0.dist-info/WHEEL
ir2json-1.0.0.dist-info/entry_points.txt
ir2json-1.0.0.dist-info/top_level.txt
ir2json-1.0.0.dist-info/RECORD
