Metadata-Version: 2.1
Name: ir2json
Version: 1.0.0
Summary: Convert Bruker OPUS dotZero files to JSON
Home-page: https://github.com/chanana/ir2json
Author: Shaurya Chanana
Author-email: schanana@wisc.edu
License: UNKNOWN
Project-URL: Bug Tracker, https://github.com/chanana/ir2json/issues
Platform: UNKNOWN
Classifier: Programming Language :: Python :: 3
Classifier: Operating System :: OS Independent
Classifier: License :: OSI Approved :: GNU Lesser General Public License v3 (LGPLv3)
Requires-Python: >=3.8
License-File: LICENSE
Requires-Dist: brukeropusreader (>=1.3.4)
